[
  {
    "prop": "validateStatus",
    "name": "审核状态",
    "align": "center",
    "width": 80
  },
  {
    "prop": "code",
    "name": "单据编码",
    "align": "center",
    "width": 130
  },
  {
    "prop": "name",
    "name": "扣罚名称",
    "width": 200
  },
  {
    "prop": "proName",
    "name": "项目名称",
    "width": 200
  },
  {
    "prop": "contractName",
    "name": "合同名称",
    "width": 200
  },
  {
    "prop": "price",
    "name": "扣罚金额",
    "align": "right",
    "width": 110
  },
  {
    "prop": "handlePerson",
    "name": "经办人员"
  },
  {
    "prop": "ifPay",
    "name": "是否结算",
    "align": "center"
  },
  {
    "prop": "payedPrice",
    "name": "结算金额",
    "align": "right",
    "width": 110
  },
  {
    "prop": "payedCode",
    "name": "结算单号",
    "width": 120,
    "align": "center"
  },
  {
    "prop": "handleDate",
    "name": "扣罚日期",
    "width": 100
  },
  {
    "prop": "inputPerson",
    "name": "登记人员",
    "width": 110
  },
  {
    "prop": "inputTime",
    "name": "登记时间",
    "width": 160
  }
]